hexchecker/__init__.py
hexchecker/hexchecker.py
hexchecker/modr/reposi.py
hexchecker-0.0.4.dist-info/METADATA
hexchecker-0.0.4.dist-info/WHEEL
hexchecker-0.0.4.dist-info/licenses/LICENSE
hexchecker-0.0.4.dist-info/RECORD
